water_tech_shrimp_mcp_demo/__init__.py
water_tech_shrimp_mcp_demo-0.1.0.dist-info/METADATA
water_tech_shrimp_mcp_demo-0.1.0.dist-info/WHEEL
water_tech_shrimp_mcp_demo-0.1.0.dist-info/entry_points.txt
water_tech_shrimp_mcp_demo-0.1.0.dist-info/RECORD
